AUTHORS
MANIFEST.in
README.md
setup.py
witsub/__init__.py
witsub/witsub.py
witsub.egg-info/PKG-INFO
witsub.egg-info/SOURCES.txt
witsub.egg-info/dependency_links.txt
witsub.egg-info/entry_points.txt
witsub.egg-info/top_level.txt