Metadata-Version: 1.1
Name: witsub
Version: 1.2.1
Summary: A command line tool to download movies subtitles
Home-page: https://github.com/nicolargo/witsub
Author: Nicolas Hennion
Author-email: nicolas@nicolargo.com
License: LGPL
Keywords: cli video subtitle
Platform: UNKNOWN
Classifier: Development Status :: 5 - Production/Stable
Classifier: Environment :: Console
Classifier: Intended Audience :: End Users/Desktop
Classifier: License :: OSI Approved :: GNU Lesser General Public License v3 (LGPLv3)
Classifier: Operating System :: OS Independent
Classifier: Natural Language :: English
Classifier: Operating System :: OS Independent
Classifier: Programming Language :: Python :: 2
Classifier: Topic :: Multimedia :: Video
Classifier: Topic :: Utilities
